recipe_caching/__init__.py
recipe_caching/caching_query.py
recipe_caching/mappers.py
recipe_caching/regions.py
recipe_caching/hooks/__init__.py
recipe_caching/hooks/modify_query.py
recipe_caching/oven/__init__.py
recipe_caching/oven/drivers/__init__.py
recipe_caching/oven/drivers/caching_oven.py
tests/__init__.py
tests/test_oven.py
tests/test_recipe.py
recipe_caching-0.6.0.dist-info/AUTHORS.rst
recipe_caching-0.6.0.dist-info/LICENSE
recipe_caching-0.6.0.dist-info/METADATA
recipe_caching-0.6.0.dist-info/WHEEL
recipe_caching-0.6.0.dist-info/entry_points.txt
recipe_caching-0.6.0.dist-info/top_level.txt
recipe_caching-0.6.0.dist-info/RECORD
