Metadata-Version: 2.1
Name: recipe-caching
Version: 0.6.0
Summary: caching for recipe library
Home-page: https://github.com/juiceinc/recipe_caching
Author: Chris Gemignani
Author-email: chris.gemignani@juiceanalytics.com
License: MIT
Platform: UNKNOWN
Classifier: Development Status :: 5 - Production/Stable
Classifier: Intended Audience :: Developers
Classifier: Natural Language :: English
Classifier: License :: OSI Approved :: MIT License
Classifier: Programming Language :: Python
Classifier: Programming Language :: Python :: 2.6
Classifier: Programming Language :: Python :: 2.7
Classifier: Programming Language :: Python :: 3.3
Classifier: Programming Language :: Python :: 3.4
Classifier: Programming Language :: Python :: 3.5
Classifier: Programming Language :: Python :: 3.6
Requires-Dist: dogpile.cache
Requires-Dist: recipe (>=0.7.2)
Requires-Dist: redis
Requires-Dist: six
Requires-Dist: sqlalchemy
Requires-Dist: structlog
